nbcourse/__init__.py
nbcourse/__main__.py
nbcourse/book.py
nbcourse/initialize.py
nbcourse/main.py
nbcourse/mydoit.py
nbcourse/nbcourse.py
nbcourse/pages.py
nbcourse/utils.py
nbcourse/reveal.js/.gitignore
nbcourse/reveal.js/.travis.yml
nbcourse/reveal.js/CONTRIBUTING.md
nbcourse/reveal.js/Gruntfile.js
nbcourse/reveal.js/LICENSE
nbcourse/reveal.js/README.md
nbcourse/reveal.js/bower.json
nbcourse/reveal.js/demo.html
nbcourse/reveal.js/index.html
nbcourse/reveal.js/package.json
nbcourse/reveal.js/css/reveal.css
nbcourse/reveal.js/css/reveal.scss
nbcourse/reveal.js/css/print/paper.css
nbcourse/reveal.js/css/print/pdf.css
nbcourse/reveal.js/css/theme/README.md
nbcourse/reveal.js/css/theme/beige.css
nbcourse/reveal.js/css/theme/black.css
nbcourse/reveal.js/css/theme/blood.css
nbcourse/reveal.js/css/theme/league.css
nbcourse/reveal.js/css/theme/moon.css
nbcourse/reveal.js/css/theme/night.css
nbcourse/reveal.js/css/theme/serif.css
nbcourse/reveal.js/css/theme/simple.css
nbcourse/reveal.js/css/theme/sky.css
nbcourse/reveal.js/css/theme/solarized.css
nbcourse/reveal.js/css/theme/white.css
nbcourse/reveal.js/css/theme/source/beige.scss
nbcourse/reveal.js/css/theme/source/black.scss
nbcourse/reveal.js/css/theme/source/blood.scss
nbcourse/reveal.js/css/theme/source/league.scss
nbcourse/reveal.js/css/theme/source/moon.scss
nbcourse/reveal.js/css/theme/source/night.scss
nbcourse/reveal.js/css/theme/source/serif.scss
nbcourse/reveal.js/css/theme/source/simple.scss
nbcourse/reveal.js/css/theme/source/sky.scss
nbcourse/reveal.js/css/theme/source/solarized.scss
nbcourse/reveal.js/css/theme/source/white.scss
nbcourse/reveal.js/css/theme/template/mixins.scss
nbcourse/reveal.js/css/theme/template/settings.scss
nbcourse/reveal.js/css/theme/template/theme.scss
nbcourse/reveal.js/js/reveal.js
nbcourse/reveal.js/lib/css/zenburn.css
nbcourse/reveal.js/lib/font/league-gothic/LICENSE
nbcourse/reveal.js/lib/font/league-gothic/league-gothic.css
nbcourse-0.3.6.dist-info/entry_points.txt
nbcourse-0.3.6.dist-info/LICENSE
nbcourse-0.3.6.dist-info/WHEEL
nbcourse-0.3.6.dist-info/METADATA
nbcourse-0.3.6.dist-info/RECORD
