Metadata-Version: 2.1
Name: nbcourse
Version: 0.3.6
Summary: Build a small website to host Jupyter notebooks as course chapters
Home-page: https://gitlab.math.unistra.fr/boileau/nbcourse
Author: Matthieu Boileau
Author-email: matthieu.boileau@math.unistra.fr
Classifier: License :: OSI Approved :: MIT License
Requires-Dist: nbconvert >= 6.0
Requires-Dist: bs4
Requires-Dist: IPython
Requires-Dist: jinja2
Requires-Dist: jupyter_contrib_nbextensions
Requires-Dist: latex
Requires-Dist: markdown
Requires-Dist: rise
Requires-Dist: pyyaml
Requires-Dist: doit >= 0.32.0
Requires-Dist: python-frontmatter
Requires-Dist: pytest ; extra == "test"
Requires-Dist: pytest-cov ; extra == "test"
Provides-Extra: test
